{
  "type": "minecraft:generic",
  "pools": [
    {
      "rolls": 1,
      "entries": [
        {
          "type": "minecraft:loot_table",
          "value": "broker:util/token_generic",
          "weight": 1,
          "functions": [
            {
              "function": "minecraft:set_components",
              "components": {
                "minecraft:profile": {
                  "id": [
                    1933560561,
                    1746748267,
                    -1615068084,
                    479659110
                  ],
                  "properties": [
                    {
                      "name": "textures",
                      "value": "eyJ0ZXh0dXJlcyI6eyJTS0lOIjp7InVybCI6Imh0dHA6Ly90ZXh0dXJlcy5taW5lY3JhZnQubmV0L3RleHR1cmUvOTE0ZmZmMmZiMjdiNTFmODZiMmM0YjIyYTM4MTAxNGRlMzJjMTNjMTJhOGY5ODlhMTg2ZmUwMzg1ZGExOWQzYyJ9fX0="
                    }
                  ]
                },
                "minecraft:item_name": "[{\"text\":\"      ❂ \",\"italic\":false,\"color\":\"#9ec0ff\"},{\"text\":\"Mithril Token\",\"color\":\"#666666\"},{\"text\":\" ❂\"}]",
                "minecraft:lore": [
                  "[{\"text\":\"------------------------\",\"italic\":false,\"color\":\"#9ec0ff\"}]",
                  "[{\"text\":\"Value:\",\"italic\":false,\"color\":\"#666666\"},{\"text\":\" \"},{\"text\":\"16,777,216 ct\",\"color\":\"gray\"}]",
                  "[{\"text\":\"\"}]",
                  "[{\"text\":\"Offhand:\",\"italic\":false,\"color\":\"#666666\"}]",
                  "[{\"text\":\"\",\"italic\":false,\"color\":\"gray\"},{\"text\":\" \",\"bold\":true},{\"text\":\" \",\"bold\":true},{\"text\":\"1 \"},{\"text\":\"❂\",\"color\":\"#9ec0ff\"},{\"text\":\"Mithril ⇒ 64 \"},{\"text\":\"❂\",\"color\":\"#dcf7f6\"},{\"text\":\"Platinum\"}]"
                ]
              }
            },
            {
              "function": "minecraft:set_custom_data",
              "tag": {
                "broker": {
                  "type": 5
                }
              }
            }
          ]
        }
      ]
    }
  ]
}